COPYING
MANIFEST.in
README.html
README.md
setup.py
bme280/__init__.py
bme280/bme280.py
bme280_upy.egg-info/PKG-INFO
bme280_upy.egg-info/SOURCES.txt
bme280_upy.egg-info/dependency_links.txt
bme280_upy.egg-info/top_level.txt
maintenance/linux-i2c.py
maintenance/linux-spi.py
maintenance/micropython-i2c-async.py
maintenance/micropython-i2c.py
maintenance/micropython-install.sh
tests/__init__.py
tests/machine.py
tests/run.sh
tests/test_i2c_dummy.py
tests/test_spi_dummy.py