Metadata-Version: 2.1
Name: bme280-upy
Version: 2.0.0
Summary: BME-280 sensor device driver with Micropython and Linux support (I2C + SPI)
Home-page: https://bues.ch/
Author: Michael Büsch
Author-email: m@bues.ch
License: GNU General Public License v2 or later
Keywords: Micropython BME280 SPI I2C Raspberry-Pi
Platform: UNKNOWN
Classifier: Development Status :: 5 - Production/Stable
Classifier: Environment :: Console
Classifier: Intended Audience :: Developers
Classifier: License :: OSI Approved :: GNU General Public License v2 or later (GPLv2+)
Classifier: Programming Language :: Python :: 3
Classifier: Programming Language :: Python :: Implementation :: CPython
Classifier: Programming Language :: Python :: Implementation :: MicroPython
Classifier: Topic :: Software Development :: Embedded Systems
Classifier: Topic :: System :: Hardware :: Hardware Drivers
License-File: COPYING
